nophp/__main__.py
nophp/conv.py
nophp/lang/__init__.py
nophp/lang/compiler.py
nophp/lang/exceptions.py
nophp/lang/lexer.py
nophp/lang/module.py
nophp/lang/modules.py
nophp/lang/pparser.py
nophp/lang/std/bcrypt.py
nophp/lang/std/db.py
nophp/lang/std/echo.py
nophp/lang/std/htmlspecialchars.py
nophp/lang/std/internal.py
nophp/lang/std/json.py
nophp/lang/std/memory.py
nophp/lang/std/primitives.py
nophp/lang/std/rand.py
nophp/lang/std/redirect.py
nophp/lang/std/session.py
nophp/lang/std/string.py
nophp/lang/std/stripe.py
nophp/lang/types.py
nophp/spindle.py
nophp/splitter.py
nophp/weaver.py
nophp-0.1.8.dist-info/LICENSE
nophp-0.1.8.dist-info/METADATA
nophp-0.1.8.dist-info/WHEEL
nophp-0.1.8.dist-info/entry_points.txt
nophp-0.1.8.dist-info/RECORD
