Metadata-Version: 2.1
Name: nophp
Version: 0.1.8
Summary: Not Only PHP - A backwards compatible language focused on modern features and flexibility.
Author: Artur Z
Author-email: doslunar8@gmail.com
Requires-Python: >=3.10,<4.0
Classifier: Programming Language :: Python :: 3
Classifier: Programming Language :: Python :: 3.10
Classifier: Programming Language :: Python :: 3.11
Requires-Dist: bcrypt (>=4.1.2,<5.0.0)
Requires-Dist: flask (>=3.0.0,<4.0.0)
Requires-Dist: pyyaml (>=6.0.1,<7.0.0)
Requires-Dist: rich (>=13.7.0,<14.0.0)
Requires-Dist: sly (>=0.5,<0.6)
Requires-Dist: stripe (>=8.8.0,<9.0.0)
